globe_server/__init__.py
globe_server/config.py
globe_server/main.py
globe_server/setup.py
globe_server/api/__init__.py
globe_server/api/media.py
globe_server/api/motor.py
globe_server/api/network.py
globe_server/api/playback.py
globe_server/api/playlist.py
globe_server/api/settings.py
globe_server/api/status.py
globe_server/api/update.py
globe_server/api/version.py
globe_server/api/websocket.py
globe_server/db/__init__.py
globe_server/db/broadcast_queue.py
globe_server/db/database.py
globe_server/db/db_events.py
globe_server/db/events.py
globe_server/db/orm.py
globe_server/db/schemas.py
globe_server/hardware/esp32_client.py
globe_server/hardware/server_hardware.py
globe_server/models/__init__.py
globe_server/models/status.py
globe_server/network_manager/mdns_manager.py
globe_server/network_manager/models.py
globe_server/network_manager/network_fsm.py
globe_server/network_manager/network_service.py
globe_server/network_manager/platform/__init__.py
globe_server/network_manager/platform/base_network.py
globe_server/network_manager/platform/linux_network.py
globe_server/network_manager/platform/windows_network.py
globe_server/playback/event_emitter.py
globe_server/playback/media_player.py
globe_server/playback/playback_context.py
globe_server/playback/playback_fsm.py
globe_server/playback/playback_service.py
globe_server/playback/playback_state.py
globe_server/playback/playback_tracker.py
globe_server/playback/media_services/__init__.py
globe_server/playback/media_services/earth_viz_service.py
globe_server/playback/media_services/vlc_service.py
globe_server/static/index-2RLu-Oe0.js
globe_server/static/index-DX6Xxgpy.css
globe_server/static/index.html
globe_server/static/vite.svg
globe_server/tools/espota.py
globe_server/utils/__init__.py
globe_server/utils/eventbus.py
globe_server/utils/files.py
globe_server/utils/uart.py
globe_server-0.0.33.dist-info/licenses/LICENSE
globe_server-0.0.33.dist-info/METADATA
globe_server-0.0.33.dist-info/WHEEL
globe_server-0.0.33.dist-info/entry_points.txt
globe_server-0.0.33.dist-info/top_level.txt
globe_server-0.0.33.dist-info/RECORD
