Metadata-Version: 2.4
Name: globe-server
Version: 0.0.33
Summary: Globe Server Backend - Webserver control of Globe
Author-email: Edward Catley <edward.catley@catleytech.com>
License-Expression: MIT
Project-URL: Homepage, https://github.com/edcatley/Globe-Software
Project-URL: Bug Reports, https://github.com/edcatley/Globe-Software/issues
Project-URL: Source, https://github.com/edcatley/Globe-Software
Keywords: globe,visualization,server,fastapi,interactive
Classifier: Development Status :: 3 - Alpha
Classifier: Intended Audience :: Developers
Classifier: Programming Language :: Python :: 3
Classifier: Programming Language :: Python :: 3.8
Classifier: Programming Language :: Python :: 3.9
Classifier: Programming Language :: Python :: 3.10
Classifier: Programming Language :: Python :: 3.11
Classifier: Operating System :: OS Independent
Classifier: Topic :: Multimedia :: Graphics :: 3D Modeling
Classifier: Topic :: Scientific/Engineering :: Visualization
Requires-Python: >=3.8
License-File: LICENSE
Requires-Dist: fastapi>=0.112.0
Requires-Dist: uvicorn[standard]>=0.30.5
Requires-Dist: pydantic>=2.8.2
Requires-Dist: python-multipart>=0.0.9
Requires-Dist: psutil>=5.8.0
Requires-Dist: requests>=2.31.0
Requires-Dist: aiofiles>=23.2.1
Requires-Dist: aiosqlite>=0.19.0
Requires-Dist: pyserial>=3.5
Requires-Dist: python-vlc>=3.0.20000
Requires-Dist: websockets>=12.0
Requires-Dist: zeroconf>=0.39.4
Requires-Dist: aiohttp>=3.9.0
Requires-Dist: numpy>=1.26.0
Requires-Dist: sqlalchemy>=2.0.0
Requires-Dist: earth-viz
Provides-Extra: dev
Requires-Dist: pytest>=7.0; extra == "dev"
Requires-Dist: pytest-asyncio>=0.21.0; extra == "dev"
Requires-Dist: black>=22.0; extra == "dev"
Requires-Dist: flake8>=5.0; extra == "dev"
Requires-Dist: mypy>=1.0; extra == "dev"
Dynamic: license-file
